nonebot_plugin_savor/__init__.py
nonebot_plugin_savor/savor.py
nonebot_plugin_savor-0.2.2.dist-info/WHEEL
nonebot_plugin_savor-0.2.2.dist-info/METADATA
nonebot_plugin_savor-0.2.2.dist-info/licenses/LICENSE
nonebot_plugin_savor-0.2.2.dist-info/RECORD
