Metadata-Version: 2.1
Name: nonebot-plugin-savor
Version: 0.2.2
Summary: NoneBot2 plugin for image analysis
License: MIT
Author-email: Akirami <Akiramiaya@outlook.com>
Requires-Python: >=3.8
Requires-Dist: Pillow<10.0.0,>=9.2.0
Requires-Dist: httpx>=0.23.0
Requires-Dist: nonebot-adapter-onebot>=2.1.3
Requires-Dist: nonebot2>=2.0.0rc1
Requires-Dist: websockets>=10.4
Project-URL: Homepage, https://github.com/A-kirami/nonebot-plugin-savor
Project-URL: Repository, https://github.com/A-kirami/nonebot-plugin-savor
